{
  "poses": {
    "拥抱": {
      "AllBody": [0.10, 0.0, 0.0],
      "UpBody": [0.10, 0.0, 0.0],
      "UpperBody": [0.18, 0.0, 0.0],
      "Head": [-0.06, 0.14, 0.04],
      "Neck": [0.05, 0.0, 0.0],
      "LeftShoulder": [0.06, 0.18, -0.15],
      "RightShoulder": [0.06, -0.18, 0.15],
      "LeftArm": [1.18, 0.48, -0.54],
      "LeftForeArm": [0.32, -0.22, 0.16],
      "RightArm": [1.18, -0.48, 0.54],
      "RightForeArm": [0.32, 0.22, -0.16],
      "LeftLeg": [0.02, 0.02, -0.04],
      "RightLeg": [0.02, -0.02, 0.04],
      "LeftLowerLeg": [-0.02, 0.0, 0.0],
      "RightLowerLeg": [-0.02, 0.0, 0.0],
      "LeftFoot": [0.02, 0.0, 0.0],
      "RightFoot": [0.02, 0.0, 0.0],
      "Skirt": [-0.05, 0.0, 0.0]
    },
    "惊讶1": {
      "AllBody": [0.099993, 0.00076, -0.018985],
      "UpBody": [-0.410999, 0.0, 0.0],
      "Head": [-0.11, 0.0, 0.0],
      "Neck": [0.0, 0.0, 0.0],
      "LeftShoulder": [0.0, 0.0, 0.0],
      "RightShoulder": [0.0, 0.0, 0.0],
      "LeftArm": [-0.003779, -0.12048, 0.727774],
      "LeftForeArm": [0.0, 0.0, 0.0],
      "RightArm": [-0.003779, 0.12048, -0.727774],
      "RightForeArm": [0.0, 0.0, 0.0],
      "LeftLeg": [0.0, 0.0, 0.0],
      "RightLeg": [0.0, 0.0, 0.0],
      "LeftLowerLeg": [0.0, 0.0, 0.0],
      "RightLowerLeg": [0.0, 0.0, 0.0],
      "LeftFoot": [0.0, 0.0, 0.0],
      "RightFoot": [0.0, 0.0, 0.0]
    },
    "惊讶2": {
      "AllBody": [0.0, 0.0, 0.0],
      "UpBody": [-0.140198, -0.056622, 0.028184],
      "Head": [0.0, 0.0, 0.0],
      "Neck": [-0.200083, 0.058371, -0.006558],
      "LeftShoulder": [0.005607, 0.079804, 0.070224],
      "RightShoulder": [0.005607, -0.079804, -0.070224],
      "LeftArm": [-0.305745, 0.006759, 0.669092],
      "LeftForeArm": [-0.605708, -0.559591, 0.809083],
      "RightArm": [-0.305745, -0.006759, -0.669092],
      "RightForeArm": [-0.68498, 0.461117, -0.853052],
      "LeftLeg": [0.0, 0.0, 0.0],
      "RightLeg": [-0.004559, -0.038967, 0.007885],
      "LeftLowerLeg": [0.0, 0.0, 0.0],
      "RightLowerLeg": [0.0, 0.0, 0.0],
      "LeftFoot": [0.0, 0.0, 0.0],
      "RightFoot": [0.0, 0.0, 0.0]
    },
    "惊讶3": {
      "AllBody": [0.0, 0.0, 0.0],
      "UpBody": [-0.49, 0.0, -0.074707],
      "Head": [0.479551, -0.050291, 0.017851],
      "Neck": [-0.74, 0.0, 0.0],
      "LeftShoulder": [0.01955, -0.449513, -0.055295],
      "RightShoulder": [0.01955, 0.449513, 0.055295],
      "LeftArm": [0.173365, -0.302315, 0.656424],
      "LeftForeArm": [0.07998, -0.095031, -0.00001],
      "RightArm": [0.124562, 0.221243, -0.623642],
      "RightForeArm": [0.082463, 0.097333, 0.002392],
      "LeftLeg": [0.0, 0.0, 0.0],
      "RightLeg": [0.0, 0.0, 0.0],
      "LeftLowerLeg": [0.0, 0.0, 0.0],
      "RightLowerLeg": [0.0, 0.0, 0.0],
      "LeftFoot": [0.0, 0.0, 0.0],
      "RightFoot": [0.0, 0.0, 0.0]
    },
    "打盹": {
      "AllBody": [0.03, 0.0, 0.0],
      "UpBody": [-0.19, 0.0, 0.0],
      "Head": [-0.609271, -0.000543, 0.021403],
      "Neck": [0.0, 0.0, 0.0],
      "LeftShoulder": [-0.054995, -0.036343, 0.344556],
      "RightShoulder": [-0.04976, 0.021245, -0.128277],
      "LeftArm": [0.665769, -0.496507, 0.107969],
      "LeftForeArm": [-0.593967, -0.472685, 1.625514],
      "RightArm": [0.52113, 0.479372, -0.451249],
      "RightForeArm": [-0.331286, 0.577922, -1.902808],
      "LeftLeg": [0.000275, -0.103247, 0.012483],
      "RightLeg": [0.000275, 0.103247, -0.012483],
      "LeftLowerLeg": [0.0, 0.0, 0.0],
      "RightLowerLeg": [0.0, 0.0, 0.0],
      "LeftFoot": [0.0, 0.0, 0.0],
      "RightFoot": [0.0, 0.0, 0.0]
    },
    "飞吻": {
      "AllBody": [0.0, 0.0, 0.0],
      "UpBody": [0.0, 0.0, 0.0],
      "Head": [0.0, 0.0, 0.0],
      "Neck": [0.0, 0.0, 0.0],
      "LeftShoulder": [0.033098, -0.006576, 0.060829],
      "RightShoulder": [0.033098, 0.006576, -0.060829],
      "LeftArm": [0.108487, -0.119686, 0.570148],
      "LeftForeArm": [0.0, 0.0, 0.0],
      "RightArm": [0.108487, 0.119686, -0.570148],
      "RightForeArm": [0.0, 0.0, 0.0],
      "LeftLeg": [0.0, 0.0, 0.0],
      "RightLeg": [0.0, 0.0, 0.0],
      "LeftLowerLeg": [0.0, 0.0, 0.0],
      "RightLowerLeg": [0.0, 0.0, 0.0],
      "LeftFoot": [0.0, 0.0, 0.0],
      "RightFoot": [0.0, 0.0, 0.0]
    },
    "抱臂": {
      "AllBody": [0.0, 0.0, 0.0],
      "UpBody": [-0.059, 0.0, 0.0],
      "Head": [-0.031, 0.0, 0.0],
      "Neck": [0.0, 0.0, 0.0],
      "LeftShoulder": [0.0, 0.0, 0.0],
      "RightShoulder": [0.0, 0.0, 0.0],
      "LeftArm": [0.0, 0.0, 0.619999],
      "LeftForeArm": [0.0, 0.0, 0.0],
      "RightArm": [0.0, 0.0, -0.619999],
      "RightForeArm": [0.0, 0.0, 0.0],
      "LeftLeg": [0.0, 0.0, 0.0],
      "RightLeg": [0.0, 0.0, 0.0],
      "LeftLowerLeg": [0.0, 0.0, 0.0],
      "RightLowerLeg": [0.0, 0.0, 0.0],
      "LeftFoot": [0.0, 0.0, 0.0],
      "RightFoot": [0.0, 0.0, 0.0]
    },
    "回眸1": {
      "AllBody": [0.0, 0.0, 0.0],
      "UpBody": [0.0, 0.0, 0.0],
      "Head": [0.0, 0.0, 0.0],
      "Neck": [0.0, 0.0, 0.0],
      "LeftShoulder": [0.0, 0.0, 0.0],
      "RightShoulder": [0.0, 0.0, 0.0],
      "LeftArm": [0.0, 0.0, 0.739999],
      "LeftForeArm": [0.0, 0.0, 0.0],
      "RightArm": [0.0, 0.0, -0.739999],
      "RightForeArm": [0.0, 0.0, 0.0],
      "LeftLeg": [0.0, 0.0, 0.0],
      "RightLeg": [0.0, 0.0, 0.0],
      "LeftLowerLeg": [0.0, 0.0, 0.0],
      "RightLowerLeg": [0.0, 0.0, 0.0],
      "LeftFoot": [0.0, 0.0, 0.0],
      "RightFoot": [0.0, 0.0, 0.0]
    },
    "回眸2": {
      "AllBody": [0.0, 0.0, 0.0],
      "UpBody": [-0.07, 0.0, 0.0],
      "Head": [0.0, 0.0, 0.0],
      "Neck": [0.0, 0.0, 0.0],
      "LeftShoulder": [0.0, 0.0, 0.0],
      "RightShoulder": [0.0, 0.0, 0.0],
      "LeftArm": [0.0, 0.0, 0.7],
      "LeftForeArm": [0.0, 0.0, 0.0],
      "RightArm": [0.069033, 0.050646, -0.675156],
      "RightForeArm": [0.0, 0.0, 0.0],
      "LeftLeg": [0.0, 0.0, 0.0],
      "RightLeg": [0.0, 0.0, 0.0],
      "LeftLowerLeg": [0.0, 0.0, 0.0],
      "RightLowerLeg": [0.0, 0.0, 0.0],
      "LeftFoot": [0.0, 0.0, 0.0],
      "RightFoot": [0.0, 0.0, 0.0]
    },
    "踢腿": {
      "AllBody": [0.0, 0.0, 0.0],
      "UpBody": [-0.027, 0.0, 0.0],
      "Head": [-0.007, 0.0, 0.0],
      "Neck": [0.0, 0.0, 0.0],
      "LeftShoulder": [0.0, 0.0, 0.0],
      "RightShoulder": [0.0, 0.0, 0.0],
      "LeftArm": [0.0, 0.0, 0.69],
      "LeftForeArm": [0.0, 0.0, 0.0],
      "RightArm": [0.0, 0.0, -0.69],
      "RightForeArm": [0.0, 0.0, 0.0],
      "LeftLeg": [0.0, 0.0, 0.0],
      "RightLeg": [0.0, 0.0, 0.0],
      "LeftLowerLeg": [0.0, 0.0, 0.0],
      "RightLowerLeg": [0.0, 0.0, 0.0],
      "LeftFoot": [0.0, 0.0, 0.0],
      "RightFoot": [0.0, 0.0, 0.0]
    },
    "捂嘴笑": {
      "AllBody": [0.0, 0.0, 0.0],
      "UpBody": [0.0, 0.0, 0.0],
      "Head": [-0.007538, 0.007836, -0.021071],
      "Neck": [0.0, 0.0, 0.0],
      "LeftShoulder": [0.0, 0.0, 0.0],
      "RightShoulder": [0.0, 0.0, 0.0],
      "LeftArm": [0.000973, -0.044308, 0.663762],
      "LeftForeArm": [0.0, 0.0, 0.0],
      "RightArm": [0.000973, 0.044308, -0.663762],
      "RightForeArm": [0.0, 0.0, 0.0],
      "LeftLeg": [0.0, 0.0, 0.0],
      "RightLeg": [0.0, 0.0, 0.0],
      "LeftLowerLeg": [0.0, 0.0, 0.0],
      "RightLowerLeg": [0.0, 0.0, 0.0],
      "LeftFoot": [0.0, 0.0, 0.0],
      "RightFoot": [0.0, 0.0, 0.0]
    },
    "躺倒抽动": {
      "AllBody": [-0.002912, 0.277405, -1.58143],
      "UpBody": [-0.063627, -0.081384, 0.487775],
      "Head": [-0.305662, -0.051387, 0.408806],
      "Neck": [0.0, 0.0, 0.0],
      "LeftShoulder": [0.448773, 0.031629, -0.020251],
      "RightShoulder": [0.031917, 0.03746, -0.024875],
      "LeftArm": [-0.701629, -0.449736, 0.944867],
      "LeftForeArm": [1.271305, -1.447103, -1.067158],
      "RightArm": [0.417385, -0.338244, 1.221259],
      "RightForeArm": [2.974934, 0.397079, 1.350131],
      "LeftLeg": [-0.04977, -0.353593, 0.231439],
      "RightLeg": [-0.188324, -0.590969, 0.562176],
      "LeftLowerLeg": [0.0, 0.0, 0.0],
      "RightLowerLeg": [0.0, 0.0, 0.0],
      "LeftFoot": [0.0, 0.0, 0.0],
      "RightFoot": [0.0, 0.0, 0.0]
    },
    "躺倒挠": {
      "AllBody": [-0.002912, 0.277405, -1.58143],
      "UpBody": [-0.063627, -0.081384, 0.487775],
      "Head": [-0.305662, -0.051387, 0.408806],
      "Neck": [0.0, 0.0, 0.0],
      "LeftShoulder": [0.448773, 0.031629, -0.020251],
      "RightShoulder": [0.031917, 0.03746, -0.024875],
      "LeftArm": [-0.701629, -0.449736, 0.944867],
      "LeftForeArm": [1.271305, -1.447103, -1.067158],
      "RightArm": [0.417385, -0.338244, 1.221259],
      "RightForeArm": [2.974934, 0.397079, 1.350131],
      "LeftLeg": [-0.04977, -0.353593, 0.231439],
      "RightLeg": [-0.188324, -0.590969, 0.562176],
      "LeftLowerLeg": [0.0, 0.0, 0.0],
      "RightLowerLeg": [0.0, 0.0, 0.0],
      "LeftFoot": [0.0, 0.0, 0.0],
      "RightFoot": [0.0, 0.0, 0.0]
    },
    "挂电话": {
      "AllBody": [0.0, 0.0, 0.0],
      "UpBody": [0.0, 0.0, 0.0],
      "Head": [0.0, 0.0, 0.0],
      "Neck": [-0.004367, -0.055421, 0.069291],
      "LeftShoulder": [-0.104481, 0.174173, -0.236255],
      "RightShoulder": [0.021068, 0.251032, -0.010653],
      "LeftArm": [1.418212, -0.941636, -0.328991],
      "LeftForeArm": [2.579048, 0.102799, -1.427069],
      "RightArm": [0.0, 0.0, -0.57],
      "RightForeArm": [0.0, 0.0, 0.0],
      "LeftLeg": [0.0, 0.0, 0.0],
      "RightLeg": [0.0, 0.0, 0.0],
      "LeftLowerLeg": [0.0, 0.0, 0.0],
      "RightLowerLeg": [0.0, 0.0, 0.0],
      "LeftFoot": [0.0, 0.0, 0.0],
      "RightFoot": [0.0, 0.0, 0.0]
    },
    "脚疼跳": {
      "AllBody": [0.0, 0.0, 0.0],
      "UpBody": [0.0, 0.0, 0.0],
      "Head": [0.0, 0.0, 0.0],
      "Neck": [0.0, 0.0, 0.0],
      "LeftShoulder": [0.0, 0.0, 0.0],
      "RightShoulder": [0.0, 0.0, 0.0],
      "LeftArm": [0.049616, 0.016184, 0.607422],
      "LeftForeArm": [0.0, 0.0, 0.0],
      "RightArm": [0.049616, -0.016184, -0.607422],
      "RightForeArm": [0.0, 0.0, 0.0],
      "LeftLeg": [0.0, 0.0, 0.0],
      "RightLeg": [0.0, 0.0, 0.0],
      "LeftLowerLeg": [0.0, 0.0, 0.0],
      "RightLowerLeg": [0.0, 0.0, 0.0],
      "LeftFoot": [0.0, 0.0, 0.0],
      "RightFoot": [0.0, 0.0, 0.0]
    },
    "吓一跳": {
      "AllBody": [0.0, 0.0, 0.0],
      "UpBody": [0.0, 0.0, 0.0],
      "Head": [0.0, 0.0, 0.0],
      "Neck": [0.0, 0.0, 0.0],
      "LeftShoulder": [0.021068, -0.251032, 0.010653],
      "RightShoulder": [0.021068, 0.251032, -0.010653],
      "LeftArm": [0.017613, 0.017718, 0.679566],
      "LeftForeArm": [0.0, 0.0, 0.0],
      "RightArm": [0.017613, -0.017718, -0.679566],
      "RightForeArm": [0.0, 0.0, 0.0],
      "LeftLeg": [0.0, 0.0, 0.0],
      "RightLeg": [0.0, 0.0, 0.0],
      "LeftLowerLeg": [0.0, 0.0, 0.0],
      "RightLowerLeg": [0.0, 0.0, 0.0],
      "LeftFoot": [0.0, 0.0, 0.0],
      "RightFoot": [0.0, 0.0, 0.0]
    },
    "傻笑": {
      "AllBody": [0.0, 0.0, 0.0],
      "UpBody": [0.0, 0.0, 0.0],
      "Head": [0.0, 0.0, 0.0],
      "Neck": [0.0, 0.0, 0.0],
      "LeftShoulder": [0.0, 0.0, 0.0],
      "RightShoulder": [0.0, 0.0, 0.0],
      "LeftArm": [0.0, 0.0, 0.75],
      "LeftForeArm": [0.0, 0.0, 0.0],
      "RightArm": [0.0, 0.0, -0.75],
      "RightForeArm": [0.0, 0.0, 0.0],
      "LeftLeg": [0.0, 0.0, 0.0],
      "RightLeg": [0.0, 0.0, 0.0],
      "LeftLowerLeg": [0.0, 0.0, 0.0],
      "RightLowerLeg": [0.0, 0.0, 0.0],
      "LeftFoot": [0.0, 0.0, 0.0],
      "RightFoot": [0.0, 0.0, 0.0]
    },
    "赌气": {
      "AllBody": [0.0, 0.0, 0.0],
      "UpBody": [0.0, 0.0, 0.0],
      "Head": [0.0, 0.0, 0.0],
      "Neck": [0.0, 0.0, 0.0],
      "LeftShoulder": [0.0, 0.0, 0.0],
      "RightShoulder": [0.0, 0.0, 0.0],
      "LeftArm": [0.0, 0.0, 0.6],
      "LeftForeArm": [0.0, 0.0, 0.0],
      "RightArm": [0.0, 0.0, -0.6],
      "RightForeArm": [0.0, 0.0, 0.0],
      "LeftLeg": [0.0, 0.0, 0.0],
      "RightLeg": [0.0, 0.0, 0.0],
      "LeftLowerLeg": [0.0, 0.0, 0.0],
      "RightLowerLeg": [0.0, 0.0, 0.0],
      "LeftFoot": [0.0, 0.0, 0.0],
      "RightFoot": [0.0, 0.0, 0.0]
    },
    "捶桌": {
      "AllBody": [0.006, 0.0, 0.0],
      "UpBody": [-0.106, 0.0, 0.0],
      "Head": [0.073, 0.0, 0.0],
      "Neck": [0.0, 0.0, 0.0],
      "LeftShoulder": [0.0, 0.0, 0.0],
      "RightShoulder": [0.0, 0.0, 0.0],
      "LeftArm": [0.031668, -0.084259, 0.658665],
      "LeftForeArm": [0.0, 0.0, 0.0],
      "RightArm": [0.031668, 0.084259, -0.658665],
      "RightForeArm": [0.0, 0.0, 0.0],
      "LeftLeg": [0.0, 0.0, 0.0],
      "RightLeg": [0.0, 0.0, 0.0],
      "LeftLowerLeg": [0.0, 0.0, 0.0],
      "RightLowerLeg": [0.0, 0.0, 0.0],
      "LeftFoot": [0.0, 0.0, 0.0],
      "RightFoot": [0.0, 0.0, 0.0]
    },
    "绊倒1": {
      "AllBody": [0.0, 0.0, 0.0],
      "UpBody": [-0.027, 0.0, 0.0],
      "Head": [-0.007, 0.0, 0.0],
      "Neck": [0.0, 0.0, 0.0],
      "LeftShoulder": [0.0, 0.0, 0.0],
      "RightShoulder": [0.0, 0.0, 0.0],
      "LeftArm": [0.0, 0.0, 0.69],
      "LeftForeArm": [0.0, 0.0, 0.0],
      "RightArm": [0.0, 0.0, -0.69],
      "RightForeArm": [0.0, 0.0, 0.0],
      "LeftLeg": [0.0, 0.0, 0.0],
      "RightLeg": [0.0, 0.0, 0.0],
      "LeftLowerLeg": [0.0, 0.0, 0.0],
      "RightLowerLeg": [0.0, 0.0, 0.0],
      "LeftFoot": [0.0, 0.0, 0.0],
      "RightFoot": [0.0, 0.0, 0.0]
    },
    "绊倒2": {
      "AllBody": [0.0, 0.0, 0.0],
      "UpBody": [-0.027, 0.0, 0.0],
      "Head": [-0.007, 0.0, 0.0],
      "Neck": [0.0, 0.0, 0.0],
      "LeftShoulder": [0.0, 0.0, 0.0],
      "RightShoulder": [0.0, 0.0, 0.0],
      "LeftArm": [0.0, 0.0, 0.69],
      "LeftForeArm": [0.0, 0.0, 0.0],
      "RightArm": [0.0, 0.0, -0.69],
      "RightForeArm": [0.0, 0.0, 0.0],
      "LeftLeg": [0.0, 0.0, 0.0],
      "RightLeg": [0.0, 0.0, 0.0],
      "LeftLowerLeg": [0.0, 0.0, 0.0],
      "RightLowerLeg": [0.0, 0.0, 0.0],
      "LeftFoot": [0.0, 0.0, 0.0],
      "RightFoot": [0.0, 0.0, 0.0]
    },
    "传送": {
      "AllBody": [0.0, 0.0, 0.0],
      "UpBody": [-0.16, 0.0, 0.0],
      "Head": [-0.09, 0.0, 0.0],
      "Neck": [0.0, 0.0, 0.0],
      "LeftShoulder": [0.0, 0.0, 0.02],
      "RightShoulder": [0.0, 0.0, -0.02],
      "LeftArm": [0.002832, -0.040368, -1.431868],
      "LeftForeArm": [0.686738, 0.504601, -0.521525],
      "RightArm": [0.002832, 0.040368, 1.431868],
      "RightForeArm": [0.686738, -0.504601, 0.521525],
      "LeftLeg": [0.0, 0.0, 0.0],
      "RightLeg": [0.0, 0.0, 0.0],
      "LeftLowerLeg": [0.0, 0.0, 0.0],
      "RightLowerLeg": [0.0, 0.0, 0.0],
      "LeftFoot": [0.0, 0.0, 0.0],
      "RightFoot": [0.0, 0.0, 0.0]
    },
    "起身": {
      "AllBody": [0.0, 0.0, 0.0],
      "UpBody": [-0.79114, 0.0, 0.0],
      "Head": [0.0, 0.0, 0.0],
      "Neck": [0.469179, -0.000367, 0.0],
      "LeftShoulder": [0.048957, -0.083377, -0.180023],
      "RightShoulder": [0.048957, 0.083377, 0.180023],
      "LeftArm": [0.851276, -0.823979, 0.147518],
      "LeftForeArm": [0.59619, 0.048527, 0.158147],
      "RightArm": [0.851276, 0.823979, -0.147518],
      "RightForeArm": [0.59619, -0.048527, -0.158147],
      "LeftLeg": [0.0, 0.0, 0.0],
      "RightLeg": [0.0, 0.0, 0.0],
      "LeftLowerLeg": [0.0, 0.0, 0.0],
      "RightLowerLeg": [0.0, 0.0, 0.0],
      "LeftFoot": [0.0, 0.0, 0.0],
      "RightFoot": [0.0, 0.0, 0.0]
    }
  }
}
